h3mlcore/__init__.py
h3mlcore/attackers/__init__.py
h3mlcore/io/BucketSeqLabelIter.py
h3mlcore/io/PipelineWorkers.py
h3mlcore/io/Preprocessor.py
h3mlcore/io/__init__.py
h3mlcore/libs/H3Kernels.py
h3mlcore/libs/__init__.py
h3mlcore/models/H3BaseActor.py
h3mlcore/models/H3BayesNet.py
h3mlcore/models/H3GPC.py
h3mlcore/models/H3GPR.py
h3mlcore/models/H3LightenedCNN.py
h3mlcore/models/H3RNNSeqClassifier.py
h3mlcore/models/H3TextClassifier.py
h3mlcore/models/H3iSVC.py
h3mlcore/models/__init__.py
h3mlcore/utils/BayesNetHelper.py
h3mlcore/utils/DatasetHelper.py
h3mlcore/utils/DatasetViewer.py
h3mlcore/utils/H3Logging.py
h3mlcore/utils/H3Plot.py
h3mlcore/utils/MxHelper.py
h3mlcore/utils/PlotHelper.py
h3mlcore/utils/__init__.py
h3mlcore-0.82.dev0.dist-info/DESCRIPTION.rst
h3mlcore-0.82.dev0.dist-info/METADATA
h3mlcore-0.82.dev0.dist-info/RECORD
h3mlcore-0.82.dev0.dist-info/WHEEL
h3mlcore-0.82.dev0.dist-info/metadata.json
h3mlcore-0.82.dev0.dist-info/top_level.txt
