Metadata-Version: 2.0
Name: h3mlcore
Version: 0.82.dev0
Summary: UNKNOWN
Home-page: https://github.com/CognutSecurity/h3mlcore
Author: Huang Xiao
Author-email: xh0217@gmail.com
License: Creative Commons license
Keywords: machine learning data mining
Platform: UNKNOWN
Classifier: Development Status :: 3 - Alpha
Classifier: Intended Audience :: Developers
Classifier: Topic :: Scientific/Engineering :: Artificial Intelligence
Classifier: Programming Language :: Python :: 2
Classifier: Programming Language :: Python :: 2.6
Classifier: Programming Language :: Python :: 2.7
Requires-Python: >=2.6, !=3.*
Requires-Dist: setuptools (==36.5.0)
Requires-Dist: nltk (==3.2.1)
Requires-Dist: mxnet (==0.12.0)
Requires-Dist: paramiko (==2.0.2)
Requires-Dist: pandas (==0.18.1)
Requires-Dist: termcolor (==1.1.0)
Requires-Dist: scipy (==0.18.0)
Requires-Dist: causality (==0.0.3)
Requires-Dist: dill (==0.2.5)
Requires-Dist: simplejson (==3.11.1)
Requires-Dist: libpgm (==1.3)
Requires-Dist: bokeh (==0.12.15)
Requires-Dist: numpy (==1.13.1)
Requires-Dist: matplotlib (==1.5.1)
Requires-Dist: javalang (==0.11.0)
Requires-Dist: scikit-learn (==0.19.1)
Requires-Dist: PyYAML (==3.12)
